metapy_toolbox/__init__.py
metapy_toolbox/bat.py
metapy_toolbox/bee_colony.py
metapy_toolbox/benchmark.py
metapy_toolbox/common_library.py
metapy_toolbox/differential_evolution.py
metapy_toolbox/firefly_algorithm.py
metapy_toolbox/functions_metrics.py
metapy_toolbox/genetic_algorithm.py
metapy_toolbox/jaya.py
metapy_toolbox/meta.py
metapy_toolbox/particle_swarm_optimization.py
metapy_toolbox/simulated_annealing.py
metapy_toolbox-2024.3.1.dist-info/LICENSE
metapy_toolbox-2024.3.1.dist-info/METADATA
metapy_toolbox-2024.3.1.dist-info/WHEEL
metapy_toolbox-2024.3.1.dist-info/top_level.txt
metapy_toolbox-2024.3.1.dist-info/RECORD
